[
  {
    "avatar": "https://picsum.photos/36/36/?random=844",
    "displayName": "Mamie Weber",
    "username": "@mamie",
    "description": "@mamie",
    "alt": "FZ"
  },
  {
    "avatar": "https://picsum.photos/36/36/?random=517",
    "displayName": "Sylvia Bartell",
    "username": "@sylvia",
    "description": "Adsuesco utrimque corrumpo vir comprehendo maxime vae.",
    "alt": "RA"
  },
  {
    "avatar": "https://picsum.photos/36/36/?random=525",
    "displayName": "Toby O'Connell",
    "username": "@toby",
    "description": "@toby",
    "alt": "LF"
  },
  {
    "avatar": "https://picsum.photos/36/36/?random=338",
    "displayName": "Rachel Zboncak",
    "username": "@rachel",
    "description": "Vitae acquiro confero impedit succurro amissio advenio.",
    "alt": "IR"
  },
  {
    "avatar": "https://picsum.photos/36/36/?random=992",
    "displayName": "Dr. Pamela Wisoky Sr.",
    "username": "@dr.",
    "description": "@dr.",
    "alt": "QA"
  },
  {
    "avatar": "https://picsum.photos/36/36/?random=155",
    "displayName": "Lillie Becker",
    "username": "@lillie",
    "description": "Voluptatibus cerno ager.",
    "alt": "FF"
  }
]
